setup.py
mongo_tools/__init__.py
mongo_tools/base.py
mongo_tools/files.py
mongo_tools/info.py
mongo_tools/profile.py
mongo_tools.egg-info/PKG-INFO
mongo_tools.egg-info/SOURCES.txt
mongo_tools.egg-info/dependency_links.txt
mongo_tools.egg-info/entry_points.txt
mongo_tools.egg-info/requires.txt
mongo_tools.egg-info/top_level.txt