Metadata-Version: 1.0
Name: mongo-tools
Version: 0.0.2
Summary: cli utility for mongodb
Home-page: https://github.com/zweifisch/mongo-tools
Author: Feng Zhou
Author-email: zf.pascal@gmail.com
License: UNKNOWN
Platform: UNKNOWN
